CHANGES.txt
CONTRIBUTORS.txt
bootstrap.py
buildout.cfg
setup.py
collective/__init__.py
collective.recipe.ant.egg-info/PKG-INFO
collective.recipe.ant.egg-info/SOURCES.txt
collective.recipe.ant.egg-info/dependency_links.txt
collective.recipe.ant.egg-info/entry_points.txt
collective.recipe.ant.egg-info/namespace_packages.txt
collective.recipe.ant.egg-info/not-zip-safe
collective.recipe.ant.egg-info/requires.txt
collective.recipe.ant.egg-info/top_level.txt
collective/recipe/__init__.py
collective/recipe/ant/README.txt
collective/recipe/ant/__init__.py
collective/recipe/ant/docs/README.txt
collective/recipe/ant/tests/__init__.py
collective/recipe/ant/tests/test_docs.py
collective/recipe/ant/tests/testdata/echo.xml