Metadata-Version: 1.0
Name: collective.recipe.ant
Version: 1.0
Summary: zc.buildout recipe for building ant (java) projects
Home-page: http://svn.plone.org/svn/collective/buildout/collective.recipe.ant/
Author: Kai Lautaportti
Author-email: kai.lautaportti@hexagonit.fi
License: ZPL
Platform: UNKNOWN
Classifier: Framework :: Buildout
Classifier: Intended Audience :: Developers
Classifier: License :: OSI Approved :: Zope Public License
Classifier: Programming Language :: Python
Classifier: Topic :: Software Development :: Build Tools
Classifier: Topic :: Software Development :: Libraries :: Python Modules
